Metadata-Version: 1.1
Name: casket
Version: 0.0.8a0
Summary: Persistent storage for ML experiments
Home-page: https://www.github.com/emanjavacas/casket
Author: Enrique Manjavacas
Author-email: enrique.manjavacas@gmail.com
License: MIT
Download-URL: https://www.github.com/emanjavacas/casket/tarball/0.0.8a0
Keywords: experiments,Machine Learning
Platform: UNKNOWN
